humansort/__init__.py
humansort/sort.py
humansort-0.1.dist-info/DESCRIPTION.rst
humansort-0.1.dist-info/METADATA
humansort-0.1.dist-info/RECORD
humansort-0.1.dist-info/WHEEL
humansort-0.1.dist-info/metadata.json
humansort-0.1.dist-info/top_level.txt
