Metadata-Version: 2.0
Name: humansort
Version: 0.1
Summary: String sorting for humans
Home-page: http://github.com/coreygirard/humansort
Author: Corey Girard
Author-email: corey.r.girard@gmail.com
License: MIT
Platform: UNKNOWN
Classifier: License :: OSI Approved :: MIT License
Classifier: Intended Audience :: Developers
Classifier: Development Status :: 3 - Alpha
